LICENSE
graphenum/__init__.py
graphenum/__main__.py
graphenum/cli.py
graphenum/entities/__init__.py
graphenum/entities/errors.py
graphenum/entities/graphql/__init__.py
graphenum/entities/graphql/properties.py
graphenum/entities/graphql/schema.py
graphenum/entities/graphql/types.py
graphenum/entities/internal.py
graphenum/logger.py
graphenum/main.py
graphenum/paths.py
graphenum/py.typed
graphenum/serdes.py
graphenum/settings.py
graphenum/sources.py
graphenum/utils.py
graphenum-0.0.3.dist-info/entry_points.txt
graphenum-0.0.3.dist-info/LICENSE
graphenum-0.0.3.dist-info/WHEEL
graphenum-0.0.3.dist-info/METADATA
graphenum-0.0.3.dist-info/RECORD
