Metadata-Version: 2.1
Name: graphenum
Version: 0.0.3
Summary: GraphQL introspection and path enumeration.
Home-page: https://escape.tech/
License: MIT
Author: Escape Technologies SAS
Author-email: ping@escape.tech
Maintainer: Swan
Maintainer-email: swan@escape.tech
Requires-Python: >=3.7,<=3.11
Classifier: License :: OSI Approved :: MIT License
Classifier: Programming Language :: Python :: 3
Classifier: Programming Language :: Python :: 3.7
Classifier: Programming Language :: Python :: 3.8
Classifier: Programming Language :: Python :: 3.9
Classifier: Programming Language :: Python :: 3.10
Requires-Dist: aiohttp (>=3.8.1,<4.0.0)
Project-URL: Repository, https://github.com/Escape-Technologies/graphenum
